{
  "prediction_date": "2026-07-14",
  "generated_at": "2026-07-13T01:13:41.811600+00:00",
  "model_version": "v8",
  "targets": {
    "NO2_zbe_d1": {
      "prediction_v1": 5.12,
      "prediction": 4.31,
      "lower": 0,
      "upper": 9.33,
      "rmse_cv": 3.915,
      "correction": -0.81,
      "foresight": {
        "base_value": 10.62,
        "positive_top": [
          {
            "feature": "traffic_volume_lag_1d",
            "value": 0.67
          },
          {
            "feature": "exp_traffic_volume_d1",
            "value": 0.45
          },
          {
            "feature": "wind_v",
            "value": 0.21
          },
          {
            "feature": "PM2.5_out",
            "value": 0.14
          },
          {
            "feature": "NO2_zbe_lag_14d",
            "value": 0.07
          }
        ],
        "negative_top": [
          {
            "feature": "NO2_zbe",
            "value": -3.03
          },
          {
            "feature": "NO2_zbe_roll_mean_7d",
            "value": -1.32
          },
          {
            "feature": "dew_point",
            "value": -0.47
          },
          {
            "feature": "traffic_occupancy_lag_7d",
            "value": -0.34
          },
          {
            "feature": "NO2_zbe_roll_max_3d",
            "value": -0.34
          }
        ],
        "narrative": {
          "es": "Error API: {\"error\":{\"message\":\"Failed to validate JSON. Please adjust your prompt. See 'failed_generation' for more details.\",\"type\":\"invalid_request_error\",\"code\":\"json_validate_failed\",\"failed_generation\":\"\"}}\n",
          "eu": "API errorea"
        }
      }
    },
    "NO2_out_d1": {
      "prediction_v1": 7.0,
      "prediction": 6.4,
      "lower": 0.65,
      "upper": 12.14,
      "rmse_cv": 4.49,
      "correction": -0.6,
      "foresight": {
        "base_value": 12.43,
        "positive_top": [
          {
            "feature": "wind_v",
            "value": 0.49
          },
          {
            "feature": "ICA_zbe_lag_14d",
            "value": 0.42
          },
          {
            "feature": "NO2_out_roll_std_3d",
            "value": 0.35
          },
          {
            "feature": "PM2.5_out",
            "value": 0.34
          },
          {
            "feature": "PM2.5_out_lag_2d",
            "value": 0.28
          }
        ],
        "negative_top": [
          {
            "feature": "NO2_out",
            "value": -3.97
          },
          {
            "feature": "temperatura_zbe",
            "value": -0.63
          },
          {
            "feature": "weather_code",
            "value": -0.4
          },
          {
            "feature": "NO2_zbe_roll_mean_7d",
            "value": -0.4
          },
          {
            "feature": "traffic_occupancy_lag_1d",
            "value": -0.39
          }
        ],
        "narrative": {
          "es": "Error API: {\"error\":{\"message\":\"Failed to validate JSON. Please adjust your prompt. See 'failed_generation' for more details.\",\"type\":\"invalid_request_error\",\"code\":\"json_validate_failed\",\"failed_generation\":\"\"}}\n",
          "eu": "API errorea"
        }
      }
    },
    "PM10_zbe_d1": {
      "prediction_v1": 18.6,
      "prediction": 18.46,
      "lower": 13.03,
      "upper": 23.88,
      "rmse_cv": 4.239,
      "correction": -0.14,
      "foresight": {
        "base_value": 12.75,
        "positive_top": [
          {
            "feature": "PM10_zbe",
            "value": 2.32
          },
          {
            "feature": "weather_code",
            "value": 0.88
          },
          {
            "feature": "ICA_zbe",
            "value": 0.88
          },
          {
            "feature": "PM10_zbe_roll_mean_30d",
            "value": 0.71
          },
          {
            "feature": "precipitation_acum_3d",
            "value": 0.39
          }
        ],
        "negative_top": [
          {
            "feature": "viento_dir_out",
            "value": -0.64
          },
          {
            "feature": "PM10_out_roll_mean_30d",
            "value": -0.24
          },
          {
            "feature": "PM10_zbe_diff_30d",
            "value": -0.15
          },
          {
            "feature": "exp_traffic_volume_d3",
            "value": -0.13
          },
          {
            "feature": "wind_u",
            "value": -0.11
          }
        ],
        "narrative": {
          "es": "Error API: {\"error\":{\"message\":\"Failed to validate JSON. Please adjust your prompt. See 'failed_generation' for more details.\",\"type\":\"invalid_request_error\",\"code\":\"json_validate_failed\",\"failed_generation\":\"\"}}\n",
          "eu": "API errorea"
        }
      }
    },
    "PM10_out_d1": {
      "prediction_v1": 16.01,
      "prediction": 16.46,
      "lower": 11.08,
      "upper": 21.85,
      "rmse_cv": 4.208,
      "correction": 0.45,
      "foresight": {
        "base_value": 10.64,
        "positive_top": [
          {
            "feature": "relative_humidity_2m",
            "value": 0.96
          },
          {
            "feature": "temp_max_dia",
            "value": 0.74
          },
          {
            "feature": "sunshine_duration",
            "value": 0.52
          },
          {
            "feature": "precipitation_acum_3d",
            "value": 0.46
          },
          {
            "feature": "PM2.5_out",
            "value": 0.43
          }
        ],
        "negative_top": [
          {
            "feature": "doy_cos",
            "value": -0.54
          },
          {
            "feature": "PM2.5_zbe_roll_max_3d",
            "value": -0.43
          },
          {
            "feature": "PM2.5_out_roll_std_14d",
            "value": -0.35
          },
          {
            "feature": "NO2_out",
            "value": -0.27
          },
          {
            "feature": "NO2_out_roll_std_3d",
            "value": -0.25
          }
        ],
        "narrative": {
          "es": "Error API: {\"error\":{\"message\":\"Failed to validate JSON. Please adjust your prompt. See 'failed_generation' for more details.\",\"type\":\"invalid_request_error\",\"code\":\"json_validate_failed\",\"failed_generation\":\"\"}}\n",
          "eu": "API errorea"
        }
      }
    },
    "PM2.5_zbe_d1": {
      "prediction_v1": 11.25,
      "prediction": 10.37,
      "lower": 6.93,
      "upper": 13.8,
      "rmse_cv": 2.68,
      "correction": -0.88,
      "foresight": {
        "base_value": 7.54,
        "positive_top": [
          {
            "feature": "PM2.5_zbe",
            "value": 1.18
          },
          {
            "feature": "ICA_zbe",
            "value": 0.68
          },
          {
            "feature": "temp_max_dia",
            "value": 0.43
          },
          {
            "feature": "ventilation_index",
            "value": 0.38
          },
          {
            "feature": "PM10_zbe_lag_2d",
            "value": 0.25
          }
        ],
        "negative_top": [
          {
            "feature": "ICA_out",
            "value": -0.41
          },
          {
            "feature": "NO2_zbe",
            "value": -0.21
          },
          {
            "feature": "NO2_zbe_lag_14d",
            "value": -0.2
          },
          {
            "feature": "PM10_zbe_lag_30d",
            "value": -0.12
          },
          {
            "feature": "boundary_layer_height",
            "value": -0.12
          }
        ],
        "narrative": {
          "es": "Error API: {\"error\":{\"message\":\"Failed to validate JSON. Please adjust your prompt. See 'failed_generation' for more details.\",\"type\":\"invalid_request_error\",\"code\":\"json_validate_failed\",\"failed_generation\":\"\"}}\n",
          "eu": "API errorea"
        }
      }
    },
    "PM2.5_out_d1": {
      "prediction_v1": 11.53,
      "prediction": 11.31,
      "lower": 7.32,
      "upper": 15.29,
      "rmse_cv": 3.111,
      "correction": -0.22,
      "foresight": {
        "base_value": 7.08,
        "positive_top": [
          {
            "feature": "PM2.5_out",
            "value": 1.43
          },
          {
            "feature": "temp_max_dia",
            "value": 0.82
          },
          {
            "feature": "PM10_zbe_lag_2d",
            "value": 0.6
          },
          {
            "feature": "sunshine_duration",
            "value": 0.4
          },
          {
            "feature": "wind_speed_10m",
            "value": 0.37
          }
        ],
        "negative_top": [
          {
            "feature": "NO2_zbe_lag_14d",
            "value": -0.27
          },
          {
            "feature": "PM2.5_zbe",
            "value": -0.22
          },
          {
            "feature": "NO2_out_roll_std_7d",
            "value": -0.21
          },
          {
            "feature": "ICA_out",
            "value": -0.2
          },
          {
            "feature": "PM10_out",
            "value": -0.2
          }
        ],
        "narrative": {
          "es": "Error API: {\"error\":{\"message\":\"Failed to validate JSON. Please adjust your prompt. See 'failed_generation' for more details.\",\"type\":\"invalid_request_error\",\"code\":\"json_validate_failed\",\"failed_generation\":\"\"}}\n",
          "eu": "API errorea"
        }
      }
    },
    "ICA_zbe_d1": {
      "prediction_v1": 18.75,
      "prediction": 18.46,
      "lower": 15.75,
      "upper": 21.17,
      "rmse_cv": 2.119,
      "correction": -0.29,
      "foresight": {
        "base_value": 18.46,
        "positive_top": [],
        "negative_top": [],
        "narrative": {
          "es": "ICA calculado con subíndices CAQI: NO2=2, PM10=18, PM2.5=17. Concentraciones: NO2=4.3, PM10=18.5, PM2.5=10.4 µg/m³.",
          "eu": "ICA CAQI azpi-indizeekin: NO2=2, PM10=18, PM2.5=17."
        }
      }
    },
    "ICA_out_d1": {
      "prediction_v1": 19.22,
      "prediction": 18.85,
      "lower": 15.98,
      "upper": 21.72,
      "rmse_cv": 2.245,
      "correction": -0.37,
      "foresight": {
        "base_value": 18.85,
        "positive_top": [],
        "negative_top": [],
        "narrative": {
          "es": "ICA calculado con subíndices CAQI: NO2=3, PM10=16, PM2.5=19. Concentraciones: NO2=6.4, PM10=16.5, PM2.5=11.3 µg/m³.",
          "eu": "ICA CAQI azpi-indizeekin: NO2=3, PM10=16, PM2.5=19."
        }
      }
    }
  }
}