{
  "NO2": {
    "beta3": -0.7524,
    "pvalue": 0.0014,
    "ci_low": -1.2136,
    "ci_high": -0.2913,
    "r2": 0.6918,
    "n_obs": 1710,
    "significant": true,
    "fe_dummies": 29,
    "se_type": "clustered_by_date",
    "formula": "pollution ~ Post + ZBE + Post_x_ZBE + C(month_year) + HDD + HDD_acum_7d + temperature_2m + precipitation + wind_speed_10m + boundary_layer_height + cloud_cover + relative_humidity_2m + sunshine_duration + is_weekend + day_of_week + month + season"
  },
  "PM10": {
    "beta3": 3.7321,
    "pvalue": 0.0,
    "ci_low": 3.2631,
    "ci_high": 4.2011,
    "r2": 0.361,
    "n_obs": 1710,
    "significant": true,
    "fe_dummies": 29,
    "se_type": "clustered_by_date",
    "formula": "pollution ~ Post + ZBE + Post_x_ZBE + C(month_year) + HDD + HDD_acum_7d + temperature_2m + precipitation + wind_speed_10m + boundary_layer_height + cloud_cover + relative_humidity_2m + sunshine_duration + is_weekend + day_of_week + month + season"
  },
  "PM2.5": {
    "beta3": 0.8984,
    "pvalue": 0.0,
    "ci_low": 0.7252,
    "ci_high": 1.0717,
    "r2": 0.3629,
    "n_obs": 1710,
    "significant": true,
    "fe_dummies": 29,
    "se_type": "clustered_by_date",
    "formula": "pollution ~ Post + ZBE + Post_x_ZBE + C(month_year) + HDD + HDD_acum_7d + temperature_2m + precipitation + wind_speed_10m + boundary_layer_height + cloud_cover + relative_humidity_2m + sunshine_duration + is_weekend + day_of_week + month + season"
  }
}