{
  "target_NO2_zbe_d1": {
    "cv_rmse": 3.5842,
    "cv_mae": 2.8765,
    "cv_r2": 0.4654,
    "cv_mape": 23.58,
    "n_features": 90
  },
  "target_NO2_out_d1": {
    "cv_rmse": 4.1076,
    "cv_mae": 3.2121,
    "cv_r2": 0.4915,
    "cv_mape": 25.56,
    "n_features": 83
  },
  "target_PM10_zbe_d1": {
    "cv_rmse": 3.7383,
    "cv_mae": 2.7443,
    "cv_r2": 0.4685,
    "cv_mape": 23.18,
    "n_features": 92
  },
  "target_PM10_out_d1": {
    "cv_rmse": 4.4664,
    "cv_mae": 3.3405,
    "cv_r2": 0.4689,
    "cv_mape": 26.53,
    "n_features": 92
  },
  "target_PM2.5_zbe_d1": {
    "cv_rmse": 2.5031,
    "cv_mae": 1.8502,
    "cv_r2": 0.5605,
    "cv_mape": 22.2,
    "n_features": 91
  },
  "target_PM2.5_out_d1": {
    "cv_rmse": 3.2705,
    "cv_mae": 2.436,
    "cv_r2": 0.5104,
    "cv_mape": 25.08,
    "n_features": 92
  },
  "target_ICA_zbe_d1": {
    "cv_rmse": 6.3271,
    "cv_mae": 4.5375,
    "cv_r2": 0.5001,
    "cv_mape": 24.92,
    "n_features": 91
  },
  "target_ICA_out_d1": {
    "cv_rmse": 8.3256,
    "cv_mae": 6.0866,
    "cv_r2": 0.4425,
    "cv_mape": 29.92,
    "n_features": 92
  }
}